Wsgi_15Watt/BaseController.py
Wsgi_15Watt/BaseTplController.py
Wsgi_15Watt/Cookie.py
Wsgi_15Watt/Exceptions.py
Wsgi_15Watt/Kernel.py
Wsgi_15Watt/Request.py
Wsgi_15Watt/Response.py
Wsgi_15Watt/Route.py
Wsgi_15Watt/__init__.py
Wsgi_15Watt/multipart.py
Wsgi_15Watt-0.9.10.dist-info/METADATA
Wsgi_15Watt-0.9.10.dist-info/WHEEL
Wsgi_15Watt-0.9.10.dist-info/top_level.txt
Wsgi_15Watt-0.9.10.dist-info/RECORD
