Metadata-Version: 2.2
Name: Wsgi_15Watt
Version: 0.9.10
Summary: A slim, fast and comfortable WSGI-Framework for Python >= 3.6.
Author-email: Thomas Siemion <pypi@15watt.net>
Project-URL: Homepage, https://wsgi.15watt.net
Project-URL: Repository, https://github.com/django15wattnet/Wsgi_15Watt
Project-URL: Issues, https://github.com/django15wattnet/Wsgi_15Watt/issues
Classifier: Programming Language :: Python :: 3.6
Classifier: License :: OSI Approved :: MIT License
Classifier: Operating System :: OS Independent
Classifier: Development Status :: 4 - Beta
Classifier: Intended Audience :: Developers
Classifier: Topic :: Internet :: WWW/HTTP :: WSGI
Requires-Python: >=3.6
